[
 {
  "default_value": null,
  "doc_type": "Sales Order",
  "docstatus": 0,
  "doctype": "Property Setter",
  "doctype_or_field": "DocField",
  "field_name": "due_date",
  "is_system_generated": 0,
  "modified": "2024-12-16 14:03:16.593798",
  "module": null,
  "name": "Sales Order-due_date-print_hide",
  "property": "print_hide",
  "property_type": "Check",
  "row_name": null,
  "value": "0"
 },
 {
  "default_value": null,
  "doc_type": "Sales Order",
  "docstatus": 0,
  "doctype": "Property Setter",
  "doctype_or_field": "DocField",
  "field_name": "payment_schedule",
  "is_system_generated": 0,
  "modified": "2024-12-16 14:03:16.599746",
  "module": null,
  "name": "Sales Order-payment_schedule-print_hide",
  "property": "print_hide",
  "property_type": "Check",
  "row_name": null,
  "value": "1"
 },
 {
  "default_value": null,
  "doc_type": "Sales Invoice",
  "docstatus": 0,
  "doctype": "Property Setter",
  "doctype_or_field": "DocField",
  "field_name": "due_date",
  "is_system_generated": 0,
  "modified": "2024-12-16 14:03:16.605359",
  "module": null,
  "name": "Sales Invoice-due_date-print_hide",
  "property": "print_hide",
  "property_type": "Check",
  "row_name": null,
  "value": "0"
 },
 {
  "default_value": null,
  "doc_type": "Sales Invoice",
  "docstatus": 0,
  "doctype": "Property Setter",
  "doctype_or_field": "DocField",
  "field_name": "payment_schedule",
  "is_system_generated": 0,
  "modified": "2024-12-16 14:03:16.611285",
  "module": null,
  "name": "Sales Invoice-payment_schedule-print_hide",
  "property": "print_hide",
  "property_type": "Check",
  "row_name": null,
  "value": "1"
 },
 {
  "default_value": null,
  "doc_type": "Purchase Order",
  "docstatus": 0,
  "doctype": "Property Setter",
  "doctype_or_field": "DocField",
  "field_name": "due_date",
  "is_system_generated": 0,
  "modified": "2024-12-16 14:03:16.615613",
  "module": null,
  "name": "Purchase Order-due_date-print_hide",
  "property": "print_hide",
  "property_type": "Check",
  "row_name": null,
  "value": "0"
 },
 {
  "default_value": null,
  "doc_type": "Purchase Order",
  "docstatus": 0,
  "doctype": "Property Setter",
  "doctype_or_field": "DocField",
  "field_name": "payment_schedule",
  "is_system_generated": 0,
  "modified": "2024-12-16 14:03:16.620268",
  "module": null,
  "name": "Purchase Order-payment_schedule-print_hide",
  "property": "print_hide",
  "property_type": "Check",
  "row_name": null,
  "value": "1"
 },
 {
  "default_value": null,
  "doc_type": "Purchase Invoice",
  "docstatus": 0,
  "doctype": "Property Setter",
  "doctype_or_field": "DocField",
  "field_name": "due_date",
  "is_system_generated": 0,
  "modified": "2024-12-16 14:03:16.624518",
  "module": null,
  "name": "Purchase Invoice-due_date-print_hide",
  "property": "print_hide",
  "property_type": "Check",
  "row_name": null,
  "value": "0"
 },
 {
  "default_value": null,
  "doc_type": "Purchase Invoice",
  "docstatus": 0,
  "doctype": "Property Setter",
  "doctype_or_field": "DocField",
  "field_name": "payment_schedule",
  "is_system_generated": 0,
  "modified": "2024-12-16 14:03:16.628705",
  "module": null,
  "name": "Purchase Invoice-payment_schedule-print_hide",
  "property": "print_hide",
  "property_type": "Check",
  "row_name": null,
  "value": "1"
 },
 {
  "default_value": null,
  "doc_type": "Supplier",
  "docstatus": 0,
  "doctype": "Property Setter",
  "doctype_or_field": "DocField",
  "field_name": "naming_series",
  "is_system_generated": 0,
  "modified": "2024-12-16 14:24:01.122360",
  "module": null,
  "name": "Supplier-naming_series-reqd",
  "property": "reqd",
  "property_type": "Check",
  "row_name": null,
  "value": "0"
 },
 {
  "default_value": null,
  "doc_type": "Supplier",
  "docstatus": 0,
  "doctype": "Property Setter",
  "doctype_or_field": "DocField",
  "field_name": "naming_series",
  "is_system_generated": 0,
  "modified": "2024-12-16 14:24:01.391985",
  "module": null,
  "name": "Supplier-naming_series-hidden",
  "property": "hidden",
  "property_type": "Check",
  "row_name": null,
  "value": "1"
 },
 {
  "default_value": null,
  "doc_type": "Customer",
  "docstatus": 0,
  "doctype": "Property Setter",
  "doctype_or_field": "DocField",
  "field_name": "naming_series",
  "is_system_generated": 0,
  "modified": "2024-12-16 14:24:02.689615",
  "module": null,
  "name": "Customer-naming_series-reqd",
  "property": "reqd",
  "property_type": "Check",
  "row_name": null,
  "value": "0"
 },
 {
  "default_value": null,
  "doc_type": "Customer",
  "docstatus": 0,
  "doctype": "Property Setter",
  "doctype_or_field": "DocField",
  "field_name": "naming_series",
  "is_system_generated": 0,
  "modified": "2024-12-16 14:24:02.962001",
  "module": null,
  "name": "Customer-naming_series-hidden",
  "property": "hidden",
  "property_type": "Check",
  "row_name": null,
  "value": "1"
 },
 {
  "default_value": null,
  "doc_type": "Sales Order",
  "docstatus": 0,
  "doctype": "Property Setter",
  "doctype_or_field": "DocField",
  "field_name": "tax_id",
  "is_system_generated": 0,
  "modified": "2024-12-16 14:24:02.991716",
  "module": null,
  "name": "Sales Order-tax_id-hidden",
  "property": "hidden",
  "property_type": "Check",
  "row_name": null,
  "value": "0"
 },
 {
  "default_value": null,
  "doc_type": "Sales Order",
  "docstatus": 0,
  "doctype": "Property Setter",
  "doctype_or_field": "DocField",
  "field_name": "tax_id",
  "is_system_generated": 0,
  "modified": "2024-12-16 14:24:03.008179",
  "module": null,
  "name": "Sales Order-tax_id-print_hide",
  "property": "print_hide",
  "property_type": "Check",
  "row_name": null,
  "value": "0"
 },
 {
  "default_value": null,
  "doc_type": "Sales Invoice",
  "docstatus": 0,
  "doctype": "Property Setter",
  "doctype_or_field": "DocField",
  "field_name": "tax_id",
  "is_system_generated": 0,
  "modified": "2024-12-16 14:24:03.024778",
  "module": null,
  "name": "Sales Invoice-tax_id-hidden",
  "property": "hidden",
  "property_type": "Check",
  "row_name": null,
  "value": "0"
 },
 {
  "default_value": null,
  "doc_type": "Sales Invoice",
  "docstatus": 0,
  "doctype": "Property Setter",
  "doctype_or_field": "DocField",
  "field_name": "tax_id",
  "is_system_generated": 0,
  "modified": "2024-12-16 14:24:03.041512",
  "module": null,
  "name": "Sales Invoice-tax_id-print_hide",
  "property": "print_hide",
  "property_type": "Check",
  "row_name": null,
  "value": "0"
 },
 {
  "default_value": null,
  "doc_type": "Delivery Note",
  "docstatus": 0,
  "doctype": "Property Setter",
  "doctype_or_field": "DocField",
  "field_name": "tax_id",
  "is_system_generated": 0,
  "modified": "2024-12-16 14:24:03.060655",
  "module": null,
  "name": "Delivery Note-tax_id-hidden",
  "property": "hidden",
  "property_type": "Check",
  "row_name": null,
  "value": "0"
 },
 {
  "default_value": null,
  "doc_type": "Delivery Note",
  "docstatus": 0,
  "doctype": "Property Setter",
  "doctype_or_field": "DocField",
  "field_name": "tax_id",
  "is_system_generated": 0,
  "modified": "2024-12-16 14:24:03.077782",
  "module": null,
  "name": "Delivery Note-tax_id-print_hide",
  "property": "print_hide",
  "property_type": "Check",
  "row_name": null,
  "value": "0"
 },
 {
  "default_value": null,
  "doc_type": "Packed Item",
  "docstatus": 0,
  "doctype": "Property Setter",
  "doctype_or_field": "DocField",
  "field_name": "rate",
  "is_system_generated": 0,
  "modified": "2024-12-16 14:24:03.094827",
  "module": null,
  "name": "Packed Item-rate-read_only",
  "property": "read_only",
  "property_type": "Check",
  "row_name": null,
  "value": "1"
 },
 {
  "default_value": null,
  "doc_type": "Sales Invoice Item",
  "docstatus": 0,
  "doctype": "Property Setter",
  "doctype_or_field": "DocField",
  "field_name": "discount_account",
  "is_system_generated": 0,
  "modified": "2024-12-16 14:24:03.110905",
  "module": null,
  "name": "Sales Invoice Item-discount_account-hidden",
  "property": "hidden",
  "property_type": "Check",
  "row_name": null,
  "value": "1"
 },
 {
  "default_value": null,
  "doc_type": "Sales Invoice Item",
  "docstatus": 0,
  "doctype": "Property Setter",
  "doctype_or_field": "DocField",
  "field_name": "discount_account",
  "is_system_generated": 0,
  "modified": "2024-12-16 14:24:03.127356",
  "module": null,
  "name": "Sales Invoice Item-discount_account-mandatory_depends_on",
  "property": "mandatory_depends_on",
  "property_type": "Code",
  "row_name": null,
  "value": ""
 },
 {
  "default_value": null,
  "doc_type": "Sales Invoice",
  "docstatus": 0,
  "doctype": "Property Setter",
  "doctype_or_field": "DocField",
  "field_name": "additional_discount_account",
  "is_system_generated": 0,
  "modified": "2024-12-16 14:24:03.147101",
  "module": null,
  "name": "Sales Invoice-additional_discount_account-hidden",
  "property": "hidden",
  "property_type": "Check",
  "row_name": null,
  "value": "1"
 },
 {
  "default_value": null,
  "doc_type": "Sales Invoice",
  "docstatus": 0,
  "doctype": "Property Setter",
  "doctype_or_field": "DocField",
  "field_name": "additional_discount_account",
  "is_system_generated": 0,
  "modified": "2024-12-16 14:24:03.162979",
  "module": null,
  "name": "Sales Invoice-additional_discount_account-mandatory_depends_on",
  "property": "mandatory_depends_on",
  "property_type": "Code",
  "row_name": null,
  "value": ""
 },
 {
  "default_value": null,
  "doc_type": "Quotation",
  "docstatus": 0,
  "doctype": "Property Setter",
  "doctype_or_field": "DocField",
  "field_name": "base_rounded_total",
  "is_system_generated": 0,
  "modified": "2024-12-16 14:24:05.157826",
  "module": null,
  "name": "Quotation-base_rounded_total-hidden",
  "property": "hidden",
  "property_type": "Check",
  "row_name": null,
  "value": "0"
 },
 {
  "default_value": null,
  "doc_type": "Quotation",
  "docstatus": 0,
  "doctype": "Property Setter",
  "doctype_or_field": "DocField",
  "field_name": "base_rounded_total",
  "is_system_generated": 0,
  "modified": "2024-12-16 14:24:05.453332",
  "module": null,
  "name": "Quotation-base_rounded_total-print_hide",
  "property": "print_hide",
  "property_type": "Check",
  "row_name": null,
  "value": "1"
 },
 {
  "default_value": null,
  "doc_type": "Quotation",
  "docstatus": 0,
  "doctype": "Property Setter",
  "doctype_or_field": "DocField",
  "field_name": "rounded_total",
  "is_system_generated": 0,
  "modified": "2024-12-16 14:24:05.473015",
  "module": null,
  "name": "Quotation-rounded_total-hidden",
  "property": "hidden",
  "property_type": "Check",
  "row_name": null,
  "value": "0"
 },
 {
  "default_value": null,
  "doc_type": "Quotation",
  "docstatus": 0,
  "doctype": "Property Setter",
  "doctype_or_field": "DocField",
  "field_name": "rounded_total",
  "is_system_generated": 0,
  "modified": "2024-12-16 14:24:05.488623",
  "module": null,
  "name": "Quotation-rounded_total-print_hide",
  "property": "print_hide",
  "property_type": "Check",
  "row_name": null,
  "value": "0"
 },
 {
  "default_value": null,
  "doc_type": "Quotation",
  "docstatus": 0,
  "doctype": "Property Setter",
  "doctype_or_field": "DocField",
  "field_name": "disable_rounded_total",
  "is_system_generated": 0,
  "modified": "2024-12-16 14:24:05.503113",
  "module": null,
  "name": "Quotation-disable_rounded_total-default",
  "property": "default",
  "property_type": "Text",
  "row_name": null,
  "value": "0"
 },
 {
  "default_value": null,
  "doc_type": "Sales Order",
  "docstatus": 0,
  "doctype": "Property Setter",
  "doctype_or_field": "DocField",
  "field_name": "base_rounded_total",
  "is_system_generated": 0,
  "modified": "2024-12-16 14:24:05.518395",
  "module": null,
  "name": "Sales Order-base_rounded_total-hidden",
  "property": "hidden",
  "property_type": "Check",
  "row_name": null,
  "value": "0"
 },
 {
  "default_value": null,
  "doc_type": "Sales Order",
  "docstatus": 0,
  "doctype": "Property Setter",
  "doctype_or_field": "DocField",
  "field_name": "base_rounded_total",
  "is_system_generated": 0,
  "modified": "2024-12-16 14:24:05.533712",
  "module": null,
  "name": "Sales Order-base_rounded_total-print_hide",
  "property": "print_hide",
  "property_type": "Check",
  "row_name": null,
  "value": "1"
 },
 {
  "default_value": null,
  "doc_type": "Sales Order",
  "docstatus": 0,
  "doctype": "Property Setter",
  "doctype_or_field": "DocField",
  "field_name": "rounded_total",
  "is_system_generated": 0,
  "modified": "2024-12-16 14:24:05.548739",
  "module": null,
  "name": "Sales Order-rounded_total-hidden",
  "property": "hidden",
  "property_type": "Check",
  "row_name": null,
  "value": "0"
 },
 {
  "default_value": null,
  "doc_type": "Sales Order",
  "docstatus": 0,
  "doctype": "Property Setter",
  "doctype_or_field": "DocField",
  "field_name": "rounded_total",
  "is_system_generated": 0,
  "modified": "2024-12-16 14:24:05.566858",
  "module": null,
  "name": "Sales Order-rounded_total-print_hide",
  "property": "print_hide",
  "property_type": "Check",
  "row_name": null,
  "value": "0"
 },
 {
  "default_value": null,
  "doc_type": "Sales Order",
  "docstatus": 0,
  "doctype": "Property Setter",
  "doctype_or_field": "DocField",
  "field_name": "disable_rounded_total",
  "is_system_generated": 0,
  "modified": "2024-12-16 14:24:05.584298",
  "module": null,
  "name": "Sales Order-disable_rounded_total-default",
  "property": "default",
  "property_type": "Text",
  "row_name": null,
  "value": "0"
 },
 {
  "default_value": null,
  "doc_type": "Sales Invoice",
  "docstatus": 0,
  "doctype": "Property Setter",
  "doctype_or_field": "DocField",
  "field_name": "base_rounded_total",
  "is_system_generated": 0,
  "modified": "2024-12-16 14:24:05.601644",
  "module": null,
  "name": "Sales Invoice-base_rounded_total-hidden",
  "property": "hidden",
  "property_type": "Check",
  "row_name": null,
  "value": "0"
 },
 {
  "default_value": null,
  "doc_type": "Sales Invoice",
  "docstatus": 0,
  "doctype": "Property Setter",
  "doctype_or_field": "DocField",
  "field_name": "base_rounded_total",
  "is_system_generated": 0,
  "modified": "2024-12-16 14:24:05.618653",
  "module": null,
  "name": "Sales Invoice-base_rounded_total-print_hide",
  "property": "print_hide",
  "property_type": "Check",
  "row_name": null,
  "value": "1"
 },
 {
  "default_value": null,
  "doc_type": "Sales Invoice",
  "docstatus": 0,
  "doctype": "Property Setter",
  "doctype_or_field": "DocField",
  "field_name": "rounded_total",
  "is_system_generated": 0,
  "modified": "2024-12-16 14:24:05.636008",
  "module": null,
  "name": "Sales Invoice-rounded_total-hidden",
  "property": "hidden",
  "property_type": "Check",
  "row_name": null,
  "value": "0"
 },
 {
  "default_value": null,
  "doc_type": "Sales Invoice",
  "docstatus": 0,
  "doctype": "Property Setter",
  "doctype_or_field": "DocField",
  "field_name": "rounded_total",
  "is_system_generated": 0,
  "modified": "2024-12-16 14:24:05.651540",
  "module": null,
  "name": "Sales Invoice-rounded_total-print_hide",
  "property": "print_hide",
  "property_type": "Check",
  "row_name": null,
  "value": "0"
 },
 {
  "default_value": null,
  "doc_type": "Sales Invoice",
  "docstatus": 0,
  "doctype": "Property Setter",
  "doctype_or_field": "DocField",
  "field_name": "disable_rounded_total",
  "is_system_generated": 0,
  "modified": "2024-12-16 14:24:05.664968",
  "module": null,
  "name": "Sales Invoice-disable_rounded_total-default",
  "property": "default",
  "property_type": "Text",
  "row_name": null,
  "value": "0"
 },
 {
  "default_value": null,
  "doc_type": "Delivery Note",
  "docstatus": 0,
  "doctype": "Property Setter",
  "doctype_or_field": "DocField",
  "field_name": "base_rounded_total",
  "is_system_generated": 0,
  "modified": "2024-12-16 14:24:05.679154",
  "module": null,
  "name": "Delivery Note-base_rounded_total-hidden",
  "property": "hidden",
  "property_type": "Check",
  "row_name": null,
  "value": "0"
 },
 {
  "default_value": null,
  "doc_type": "Delivery Note",
  "docstatus": 0,
  "doctype": "Property Setter",
  "doctype_or_field": "DocField",
  "field_name": "base_rounded_total",
  "is_system_generated": 0,
  "modified": "2024-12-16 14:24:05.694454",
  "module": null,
  "name": "Delivery Note-base_rounded_total-print_hide",
  "property": "print_hide",
  "property_type": "Check",
  "row_name": null,
  "value": "1"
 },
 {
  "default_value": null,
  "doc_type": "Delivery Note",
  "docstatus": 0,
  "doctype": "Property Setter",
  "doctype_or_field": "DocField",
  "field_name": "rounded_total",
  "is_system_generated": 0,
  "modified": "2024-12-16 14:24:05.710462",
  "module": null,
  "name": "Delivery Note-rounded_total-hidden",
  "property": "hidden",
  "property_type": "Check",
  "row_name": null,
  "value": "0"
 },
 {
  "default_value": null,
  "doc_type": "Delivery Note",
  "docstatus": 0,
  "doctype": "Property Setter",
  "doctype_or_field": "DocField",
  "field_name": "rounded_total",
  "is_system_generated": 0,
  "modified": "2024-12-16 14:24:05.727268",
  "module": null,
  "name": "Delivery Note-rounded_total-print_hide",
  "property": "print_hide",
  "property_type": "Check",
  "row_name": null,
  "value": "0"
 },
 {
  "default_value": null,
  "doc_type": "Delivery Note",
  "docstatus": 0,
  "doctype": "Property Setter",
  "doctype_or_field": "DocField",
  "field_name": "disable_rounded_total",
  "is_system_generated": 0,
  "modified": "2024-12-16 14:24:05.740336",
  "module": null,
  "name": "Delivery Note-disable_rounded_total-default",
  "property": "default",
  "property_type": "Text",
  "row_name": null,
  "value": "0"
 },
 {
  "default_value": null,
  "doc_type": "Supplier Quotation",
  "docstatus": 0,
  "doctype": "Property Setter",
  "doctype_or_field": "DocField",
  "field_name": "base_rounded_total",
  "is_system_generated": 0,
  "modified": "2024-12-16 14:24:05.753985",
  "module": null,
  "name": "Supplier Quotation-base_rounded_total-hidden",
  "property": "hidden",
  "property_type": "Check",
  "row_name": null,
  "value": "0"
 },
 {
  "default_value": null,
  "doc_type": "Supplier Quotation",
  "docstatus": 0,
  "doctype": "Property Setter",
  "doctype_or_field": "DocField",
  "field_name": "base_rounded_total",
  "is_system_generated": 0,
  "modified": "2024-12-16 14:24:05.768573",
  "module": null,
  "name": "Supplier Quotation-base_rounded_total-print_hide",
  "property": "print_hide",
  "property_type": "Check",
  "row_name": null,
  "value": "1"
 },
 {
  "default_value": null,
  "doc_type": "Supplier Quotation",
  "docstatus": 0,
  "doctype": "Property Setter",
  "doctype_or_field": "DocField",
  "field_name": "rounded_total",
  "is_system_generated": 0,
  "modified": "2024-12-16 14:24:05.782577",
  "module": null,
  "name": "Supplier Quotation-rounded_total-hidden",
  "property": "hidden",
  "property_type": "Check",
  "row_name": null,
  "value": "0"
 },
 {
  "default_value": null,
  "doc_type": "Supplier Quotation",
  "docstatus": 0,
  "doctype": "Property Setter",
  "doctype_or_field": "DocField",
  "field_name": "rounded_total",
  "is_system_generated": 0,
  "modified": "2024-12-16 14:24:05.796269",
  "module": null,
  "name": "Supplier Quotation-rounded_total-print_hide",
  "property": "print_hide",
  "property_type": "Check",
  "row_name": null,
  "value": "0"
 },
 {
  "default_value": null,
  "doc_type": "Supplier Quotation",
  "docstatus": 0,
  "doctype": "Property Setter",
  "doctype_or_field": "DocField",
  "field_name": "disable_rounded_total",
  "is_system_generated": 0,
  "modified": "2024-12-16 14:24:05.810369",
  "module": null,
  "name": "Supplier Quotation-disable_rounded_total-default",
  "property": "default",
  "property_type": "Text",
  "row_name": null,
  "value": "0"
 },
 {
  "default_value": null,
  "doc_type": "Purchase Order",
  "docstatus": 0,
  "doctype": "Property Setter",
  "doctype_or_field": "DocField",
  "field_name": "base_rounded_total",
  "is_system_generated": 0,
  "modified": "2024-12-16 14:24:05.826087",
  "module": null,
  "name": "Purchase Order-base_rounded_total-hidden",
  "property": "hidden",
  "property_type": "Check",
  "row_name": null,
  "value": "0"
 },
 {
  "default_value": null,
  "doc_type": "Purchase Order",
  "docstatus": 0,
  "doctype": "Property Setter",
  "doctype_or_field": "DocField",
  "field_name": "base_rounded_total",
  "is_system_generated": 0,
  "modified": "2024-12-16 14:24:05.842589",
  "module": null,
  "name": "Purchase Order-base_rounded_total-print_hide",
  "property": "print_hide",
  "property_type": "Check",
  "row_name": null,
  "value": "1"
 },
 {
  "default_value": null,
  "doc_type": "Purchase Order",
  "docstatus": 0,
  "doctype": "Property Setter",
  "doctype_or_field": "DocField",
  "field_name": "rounded_total",
  "is_system_generated": 0,
  "modified": "2024-12-16 14:24:05.858050",
  "module": null,
  "name": "Purchase Order-rounded_total-hidden",
  "property": "hidden",
  "property_type": "Check",
  "row_name": null,
  "value": "0"
 },
 {
  "default_value": null,
  "doc_type": "Purchase Order",
  "docstatus": 0,
  "doctype": "Property Setter",
  "doctype_or_field": "DocField",
  "field_name": "rounded_total",
  "is_system_generated": 0,
  "modified": "2024-12-16 14:24:05.874176",
  "module": null,
  "name": "Purchase Order-rounded_total-print_hide",
  "property": "print_hide",
  "property_type": "Check",
  "row_name": null,
  "value": "0"
 },
 {
  "default_value": null,
  "doc_type": "Purchase Order",
  "docstatus": 0,
  "doctype": "Property Setter",
  "doctype_or_field": "DocField",
  "field_name": "disable_rounded_total",
  "is_system_generated": 0,
  "modified": "2024-12-16 14:24:05.891415",
  "module": null,
  "name": "Purchase Order-disable_rounded_total-default",
  "property": "default",
  "property_type": "Text",
  "row_name": null,
  "value": "0"
 },
 {
  "default_value": null,
  "doc_type": "Purchase Invoice",
  "docstatus": 0,
  "doctype": "Property Setter",
  "doctype_or_field": "DocField",
  "field_name": "base_rounded_total",
  "is_system_generated": 0,
  "modified": "2024-12-16 14:24:05.907941",
  "module": null,
  "name": "Purchase Invoice-base_rounded_total-hidden",
  "property": "hidden",
  "property_type": "Check",
  "row_name": null,
  "value": "0"
 },
 {
  "default_value": null,
  "doc_type": "Purchase Invoice",
  "docstatus": 0,
  "doctype": "Property Setter",
  "doctype_or_field": "DocField",
  "field_name": "base_rounded_total",
  "is_system_generated": 0,
  "modified": "2024-12-16 14:24:05.926217",
  "module": null,
  "name": "Purchase Invoice-base_rounded_total-print_hide",
  "property": "print_hide",
  "property_type": "Check",
  "row_name": null,
  "value": "1"
 },
 {
  "default_value": null,
  "doc_type": "Purchase Invoice",
  "docstatus": 0,
  "doctype": "Property Setter",
  "doctype_or_field": "DocField",
  "field_name": "rounded_total",
  "is_system_generated": 0,
  "modified": "2024-12-16 14:24:05.943319",
  "module": null,
  "name": "Purchase Invoice-rounded_total-hidden",
  "property": "hidden",
  "property_type": "Check",
  "row_name": null,
  "value": "0"
 },
 {
  "default_value": null,
  "doc_type": "Purchase Invoice",
  "docstatus": 0,
  "doctype": "Property Setter",
  "doctype_or_field": "DocField",
  "field_name": "rounded_total",
  "is_system_generated": 0,
  "modified": "2024-12-16 14:24:05.960992",
  "module": null,
  "name": "Purchase Invoice-rounded_total-print_hide",
  "property": "print_hide",
  "property_type": "Check",
  "row_name": null,
  "value": "0"
 },
 {
  "default_value": null,
  "doc_type": "Purchase Invoice",
  "docstatus": 0,
  "doctype": "Property Setter",
  "doctype_or_field": "DocField",
  "field_name": "disable_rounded_total",
  "is_system_generated": 0,
  "modified": "2024-12-16 14:24:05.974414",
  "module": null,
  "name": "Purchase Invoice-disable_rounded_total-default",
  "property": "default",
  "property_type": "Text",
  "row_name": null,
  "value": "0"
 },
 {
  "default_value": null,
  "doc_type": "Purchase Receipt",
  "docstatus": 0,
  "doctype": "Property Setter",
  "doctype_or_field": "DocField",
  "field_name": "base_rounded_total",
  "is_system_generated": 0,
  "modified": "2024-12-16 14:24:05.988012",
  "module": null,
  "name": "Purchase Receipt-base_rounded_total-hidden",
  "property": "hidden",
  "property_type": "Check",
  "row_name": null,
  "value": "0"
 },
 {
  "default_value": null,
  "doc_type": "Purchase Receipt",
  "docstatus": 0,
  "doctype": "Property Setter",
  "doctype_or_field": "DocField",
  "field_name": "base_rounded_total",
  "is_system_generated": 0,
  "modified": "2024-12-16 14:24:06.001380",
  "module": null,
  "name": "Purchase Receipt-base_rounded_total-print_hide",
  "property": "print_hide",
  "property_type": "Check",
  "row_name": null,
  "value": "1"
 },
 {
  "default_value": null,
  "doc_type": "Purchase Receipt",
  "docstatus": 0,
  "doctype": "Property Setter",
  "doctype_or_field": "DocField",
  "field_name": "rounded_total",
  "is_system_generated": 0,
  "modified": "2024-12-16 14:24:06.016106",
  "module": null,
  "name": "Purchase Receipt-rounded_total-hidden",
  "property": "hidden",
  "property_type": "Check",
  "row_name": null,
  "value": "0"
 },
 {
  "default_value": null,
  "doc_type": "Purchase Receipt",
  "docstatus": 0,
  "doctype": "Property Setter",
  "doctype_or_field": "DocField",
  "field_name": "rounded_total",
  "is_system_generated": 0,
  "modified": "2024-12-16 14:24:06.030959",
  "module": null,
  "name": "Purchase Receipt-rounded_total-print_hide",
  "property": "print_hide",
  "property_type": "Check",
  "row_name": null,
  "value": "0"
 },
 {
  "default_value": null,
  "doc_type": "Purchase Receipt",
  "docstatus": 0,
  "doctype": "Property Setter",
  "doctype_or_field": "DocField",
  "field_name": "disable_rounded_total",
  "is_system_generated": 0,
  "modified": "2024-12-16 14:24:06.045954",
  "module": null,
  "name": "Purchase Receipt-disable_rounded_total-default",
  "property": "default",
  "property_type": "Text",
  "row_name": null,
  "value": "0"
 },
 {
  "default_value": null,
  "doc_type": "Quotation",
  "docstatus": 0,
  "doctype": "Property Setter",
  "doctype_or_field": "DocField",
  "field_name": "in_words",
  "is_system_generated": 0,
  "modified": "2024-12-16 14:24:06.061794",
  "module": null,
  "name": "Quotation-in_words-hidden",
  "property": "hidden",
  "property_type": "Check",
  "row_name": null,
  "value": "0"
 },
 {
  "default_value": null,
  "doc_type": "Quotation",
  "docstatus": 0,
  "doctype": "Property Setter",
  "doctype_or_field": "DocField",
  "field_name": "in_words",
  "is_system_generated": 0,
  "modified": "2024-12-16 14:24:06.078648",
  "module": null,
  "name": "Quotation-in_words-print_hide",
  "property": "print_hide",
  "property_type": "Check",
  "row_name": null,
  "value": "0"
 },
 {
  "default_value": null,
  "doc_type": "Sales Order",
  "docstatus": 0,
  "doctype": "Property Setter",
  "doctype_or_field": "DocField",
  "field_name": "in_words",
  "is_system_generated": 0,
  "modified": "2024-12-16 14:24:06.097519",
  "module": null,
  "name": "Sales Order-in_words-hidden",
  "property": "hidden",
  "property_type": "Check",
  "row_name": null,
  "value": "0"
 },
 {
  "default_value": null,
  "doc_type": "Sales Order",
  "docstatus": 0,
  "doctype": "Property Setter",
  "doctype_or_field": "DocField",
  "field_name": "in_words",
  "is_system_generated": 0,
  "modified": "2024-12-16 14:24:06.114423",
  "module": null,
  "name": "Sales Order-in_words-print_hide",
  "property": "print_hide",
  "property_type": "Check",
  "row_name": null,
  "value": "0"
 },
 {
  "default_value": null,
  "doc_type": "Sales Invoice",
  "docstatus": 0,
  "doctype": "Property Setter",
  "doctype_or_field": "DocField",
  "field_name": "in_words",
  "is_system_generated": 0,
  "modified": "2024-12-16 14:24:06.131214",
  "module": null,
  "name": "Sales Invoice-in_words-hidden",
  "property": "hidden",
  "property_type": "Check",
  "row_name": null,
  "value": "0"
 },
 {
  "default_value": null,
  "doc_type": "Sales Invoice",
  "docstatus": 0,
  "doctype": "Property Setter",
  "doctype_or_field": "DocField",
  "field_name": "in_words",
  "is_system_generated": 0,
  "modified": "2024-12-16 14:24:06.150792",
  "module": null,
  "name": "Sales Invoice-in_words-print_hide",
  "property": "print_hide",
  "property_type": "Check",
  "row_name": null,
  "value": "0"
 },
 {
  "default_value": null,
  "doc_type": "Delivery Note",
  "docstatus": 0,
  "doctype": "Property Setter",
  "doctype_or_field": "DocField",
  "field_name": "in_words",
  "is_system_generated": 0,
  "modified": "2024-12-16 14:24:06.170018",
  "module": null,
  "name": "Delivery Note-in_words-hidden",
  "property": "hidden",
  "property_type": "Check",
  "row_name": null,
  "value": "0"
 },
 {
  "default_value": null,
  "doc_type": "Delivery Note",
  "docstatus": 0,
  "doctype": "Property Setter",
  "doctype_or_field": "DocField",
  "field_name": "in_words",
  "is_system_generated": 0,
  "modified": "2024-12-16 14:24:06.185986",
  "module": null,
  "name": "Delivery Note-in_words-print_hide",
  "property": "print_hide",
  "property_type": "Check",
  "row_name": null,
  "value": "0"
 },
 {
  "default_value": null,
  "doc_type": "Supplier Quotation",
  "docstatus": 0,
  "doctype": "Property Setter",
  "doctype_or_field": "DocField",
  "field_name": "in_words",
  "is_system_generated": 0,
  "modified": "2024-12-16 14:24:06.203098",
  "module": null,
  "name": "Supplier Quotation-in_words-hidden",
  "property": "hidden",
  "property_type": "Check",
  "row_name": null,
  "value": "0"
 },
 {
  "default_value": null,
  "doc_type": "Supplier Quotation",
  "docstatus": 0,
  "doctype": "Property Setter",
  "doctype_or_field": "DocField",
  "field_name": "in_words",
  "is_system_generated": 0,
  "modified": "2024-12-16 14:24:06.225752",
  "module": null,
  "name": "Supplier Quotation-in_words-print_hide",
  "property": "print_hide",
  "property_type": "Check",
  "row_name": null,
  "value": "0"
 },
 {
  "default_value": null,
  "doc_type": "Purchase Order",
  "docstatus": 0,
  "doctype": "Property Setter",
  "doctype_or_field": "DocField",
  "field_name": "in_words",
  "is_system_generated": 0,
  "modified": "2024-12-16 14:24:06.242946",
  "module": null,
  "name": "Purchase Order-in_words-hidden",
  "property": "hidden",
  "property_type": "Check",
  "row_name": null,
  "value": "0"
 },
 {
  "default_value": null,
  "doc_type": "Purchase Order",
  "docstatus": 0,
  "doctype": "Property Setter",
  "doctype_or_field": "DocField",
  "field_name": "in_words",
  "is_system_generated": 0,
  "modified": "2024-12-16 14:24:06.266717",
  "module": null,
  "name": "Purchase Order-in_words-print_hide",
  "property": "print_hide",
  "property_type": "Check",
  "row_name": null,
  "value": "0"
 },
 {
  "default_value": null,
  "doc_type": "Purchase Invoice",
  "docstatus": 0,
  "doctype": "Property Setter",
  "doctype_or_field": "DocField",
  "field_name": "in_words",
  "is_system_generated": 0,
  "modified": "2024-12-16 14:24:06.283530",
  "module": null,
  "name": "Purchase Invoice-in_words-hidden",
  "property": "hidden",
  "property_type": "Check",
  "row_name": null,
  "value": "0"
 },
 {
  "default_value": null,
  "doc_type": "Purchase Invoice",
  "docstatus": 0,
  "doctype": "Property Setter",
  "doctype_or_field": "DocField",
  "field_name": "in_words",
  "is_system_generated": 0,
  "modified": "2024-12-16 14:24:06.301756",
  "module": null,
  "name": "Purchase Invoice-in_words-print_hide",
  "property": "print_hide",
  "property_type": "Check",
  "row_name": null,
  "value": "0"
 },
 {
  "default_value": null,
  "doc_type": "Purchase Receipt",
  "docstatus": 0,
  "doctype": "Property Setter",
  "doctype_or_field": "DocField",
  "field_name": "in_words",
  "is_system_generated": 0,
  "modified": "2024-12-16 14:24:06.318820",
  "module": null,
  "name": "Purchase Receipt-in_words-hidden",
  "property": "hidden",
  "property_type": "Check",
  "row_name": null,
  "value": "0"
 },
 {
  "default_value": null,
  "doc_type": "Purchase Receipt",
  "docstatus": 0,
  "doctype": "Property Setter",
  "doctype_or_field": "DocField",
  "field_name": "in_words",
  "is_system_generated": 0,
  "modified": "2024-12-16 14:24:06.338891",
  "module": null,
  "name": "Purchase Receipt-in_words-print_hide",
  "property": "print_hide",
  "property_type": "Check",
  "row_name": null,
  "value": "0"
 },
 {
  "default_value": null,
  "doc_type": "Item",
  "docstatus": 0,
  "doctype": "Property Setter",
  "doctype_or_field": "DocField",
  "field_name": "naming_series",
  "is_system_generated": 0,
  "modified": "2024-12-16 14:24:08.431572",
  "module": null,
  "name": "Item-naming_series-reqd",
  "property": "reqd",
  "property_type": "Check",
  "row_name": null,
  "value": "0"
 },
 {
  "default_value": null,
  "doc_type": "Item",
  "docstatus": 0,
  "doctype": "Property Setter",
  "doctype_or_field": "DocField",
  "field_name": "naming_series",
  "is_system_generated": 0,
  "modified": "2024-12-16 14:24:08.744856",
  "module": null,
  "name": "Item-naming_series-hidden",
  "property": "hidden",
  "property_type": "Check",
  "row_name": null,
  "value": "1"
 },
 {
  "default_value": null,
  "doc_type": "Item",
  "docstatus": 0,
  "doctype": "Property Setter",
  "doctype_or_field": "DocField",
  "field_name": "item_code",
  "is_system_generated": 0,
  "modified": "2024-12-16 14:24:08.760771",
  "module": null,
  "name": "Item-item_code-hidden",
  "property": "hidden",
  "property_type": "Check",
  "row_name": null,
  "value": "0"
 },
 {
  "default_value": null,
  "doc_type": "Item",
  "docstatus": 0,
  "doctype": "Property Setter",
  "doctype_or_field": "DocField",
  "field_name": "item_code",
  "is_system_generated": 0,
  "modified": "2024-12-16 14:24:08.777258",
  "module": null,
  "name": "Item-item_code-reqd",
  "property": "reqd",
  "property_type": "Check",
  "row_name": null,
  "value": "1"
 },
 {
  "default_value": null,
  "doc_type": "Item Barcode",
  "docstatus": 0,
  "doctype": "Property Setter",
  "doctype_or_field": "DocField",
  "field_name": "barcode",
  "is_system_generated": 1,
  "modified": "2024-12-16 14:24:08.796352",
  "module": null,
  "name": "Item Barcode-barcode-hidden",
  "property": "hidden",
  "property_type": "Check",
  "row_name": null,
  "value": "0"
 },
 {
  "default_value": null,
  "doc_type": "POS Invoice Item",
  "docstatus": 0,
  "doctype": "Property Setter",
  "doctype_or_field": "DocField",
  "field_name": "barcode",
  "is_system_generated": 1,
  "modified": "2024-12-16 14:24:08.816632",
  "module": null,
  "name": "POS Invoice Item-barcode-hidden",
  "property": "hidden",
  "property_type": "Check",
  "row_name": null,
  "value": "0"
 },
 {
  "default_value": null,
  "doc_type": "Purchase Receipt Item",
  "docstatus": 0,
  "doctype": "Property Setter",
  "doctype_or_field": "DocField",
  "field_name": "barcode",
  "is_system_generated": 1,
  "modified": "2024-12-16 14:24:08.836204",
  "module": null,
  "name": "Purchase Receipt Item-barcode-hidden",
  "property": "hidden",
  "property_type": "Check",
  "row_name": null,
  "value": "0"
 },
 {
  "default_value": null,
  "doc_type": "Sales Invoice Item",
  "docstatus": 0,
  "doctype": "Property Setter",
  "doctype_or_field": "DocField",
  "field_name": "barcode",
  "is_system_generated": 1,
  "modified": "2024-12-16 14:24:08.852154",
  "module": null,
  "name": "Sales Invoice Item-barcode-hidden",
  "property": "hidden",
  "property_type": "Check",
  "row_name": null,
  "value": "0"
 },
 {
  "default_value": null,
  "doc_type": "Stock Reconciliation Item",
  "docstatus": 0,
  "doctype": "Property Setter",
  "doctype_or_field": "DocField",
  "field_name": "barcode",
  "is_system_generated": 1,
  "modified": "2024-12-16 14:24:08.867076",
  "module": null,
  "name": "Stock Reconciliation Item-barcode-hidden",
  "property": "hidden",
  "property_type": "Check",
  "row_name": null,
  "value": "0"
 },
 {
  "default_value": null,
  "doc_type": "Delivery Note Item",
  "docstatus": 0,
  "doctype": "Property Setter",
  "doctype_or_field": "DocField",
  "field_name": "barcode",
  "is_system_generated": 1,
  "modified": "2024-12-16 14:24:08.882679",
  "module": null,
  "name": "Delivery Note Item-barcode-hidden",
  "property": "hidden",
  "property_type": "Check",
  "row_name": null,
  "value": "0"
 },
 {
  "default_value": null,
  "doc_type": "Job Card",
  "docstatus": 0,
  "doctype": "Property Setter",
  "doctype_or_field": "DocField",
  "field_name": "barcode",
  "is_system_generated": 1,
  "modified": "2024-12-16 14:24:08.899282",
  "module": null,
  "name": "Job Card-barcode-hidden",
  "property": "hidden",
  "property_type": "Check",
  "row_name": null,
  "value": "0"
 },
 {
  "default_value": null,
  "doc_type": "Stock Entry Detail",
  "docstatus": 0,
  "doctype": "Property Setter",
  "doctype_or_field": "DocField",
  "field_name": "barcode",
  "is_system_generated": 1,
  "modified": "2024-12-16 14:24:08.914944",
  "module": null,
  "name": "Stock Entry Detail-barcode-hidden",
  "property": "hidden",
  "property_type": "Check",
  "row_name": null,
  "value": "0"
 },
 {
  "default_value": null,
  "doc_type": "Item",
  "docstatus": 0,
  "doctype": "Property Setter",
  "doctype_or_field": "DocField",
  "field_name": "barcodes",
  "is_system_generated": 1,
  "modified": "2024-12-16 14:24:08.932965",
  "module": null,
  "name": "Item-barcodes-hidden",
  "property": "hidden",
  "property_type": "Check",
  "row_name": null,
  "value": "0"
 },
 {
  "default_value": null,
  "doc_type": "Purchase Receipt",
  "docstatus": 0,
  "doctype": "Property Setter",
  "doctype_or_field": "DocField",
  "field_name": "scan_barcode",
  "is_system_generated": 1,
  "modified": "2024-12-16 14:24:08.948101",
  "module": null,
  "name": "Purchase Receipt-scan_barcode-hidden",
  "property": "hidden",
  "property_type": "Check",
  "row_name": null,
  "value": "0"
 },
 {
  "default_value": null,
  "doc_type": "Quotation",
  "docstatus": 0,
  "doctype": "Property Setter",
  "doctype_or_field": "DocField",
  "field_name": "scan_barcode",
  "is_system_generated": 1,
  "modified": "2024-12-16 14:24:08.963302",
  "module": null,
  "name": "Quotation-scan_barcode-hidden",
  "property": "hidden",
  "property_type": "Check",
  "row_name": null,
  "value": "0"
 },
 {
  "default_value": null,
  "doc_type": "Pick List",
  "docstatus": 0,
  "doctype": "Property Setter",
  "doctype_or_field": "DocField",
  "field_name": "scan_barcode",
  "is_system_generated": 1,
  "modified": "2024-12-16 14:24:08.979365",
  "module": null,
  "name": "Pick List-scan_barcode-hidden",
  "property": "hidden",
  "property_type": "Check",
  "row_name": null,
  "value": "0"
 },
 {
  "default_value": null,
  "doc_type": "Stock Reconciliation",
  "docstatus": 0,
  "doctype": "Property Setter",
  "doctype_or_field": "DocField",
  "field_name": "scan_barcode",
  "is_system_generated": 1,
  "modified": "2024-12-16 14:24:08.995762",
  "module": null,
  "name": "Stock Reconciliation-scan_barcode-hidden",
  "property": "hidden",
  "property_type": "Check",
  "row_name": null,
  "value": "0"
 },
 {
  "default_value": null,
  "doc_type": "Purchase Order",
  "docstatus": 0,
  "doctype": "Property Setter",
  "doctype_or_field": "DocField",
  "field_name": "scan_barcode",
  "is_system_generated": 1,
  "modified": "2024-12-16 14:24:09.013150",
  "module": null,
  "name": "Purchase Order-scan_barcode-hidden",
  "property": "hidden",
  "property_type": "Check",
  "row_name": null,
  "value": "0"
 },
 {
  "default_value": null,
  "doc_type": "POS Invoice",
  "docstatus": 0,
  "doctype": "Property Setter",
  "doctype_or_field": "DocField",
  "field_name": "scan_barcode",
  "is_system_generated": 1,
  "modified": "2024-12-16 14:24:09.031648",
  "module": null,
  "name": "POS Invoice-scan_barcode-hidden",
  "property": "hidden",
  "property_type": "Check",
  "row_name": null,
  "value": "0"
 },
 {
  "default_value": null,
  "doc_type": "Purchase Invoice",
  "docstatus": 0,
  "doctype": "Property Setter",
  "doctype_or_field": "DocField",
  "field_name": "scan_barcode",
  "is_system_generated": 1,
  "modified": "2024-12-16 14:24:09.047224",
  "module": null,
  "name": "Purchase Invoice-scan_barcode-hidden",
  "property": "hidden",
  "property_type": "Check",
  "row_name": null,
  "value": "0"
 },
 {
  "default_value": null,
  "doc_type": "Sales Order",
  "docstatus": 0,
  "doctype": "Property Setter",
  "doctype_or_field": "DocField",
  "field_name": "scan_barcode",
  "is_system_generated": 1,
  "modified": "2024-12-16 14:24:09.064702",
  "module": null,
  "name": "Sales Order-scan_barcode-hidden",
  "property": "hidden",
  "property_type": "Check",
  "row_name": null,
  "value": "0"
 },
 {
  "default_value": null,
  "doc_type": "Delivery Note",
  "docstatus": 0,
  "doctype": "Property Setter",
  "doctype_or_field": "DocField",
  "field_name": "scan_barcode",
  "is_system_generated": 1,
  "modified": "2024-12-16 14:24:09.082447",
  "module": null,
  "name": "Delivery Note-scan_barcode-hidden",
  "property": "hidden",
  "property_type": "Check",
  "row_name": null,
  "value": "0"
 },
 {
  "default_value": null,
  "doc_type": "Sales Invoice",
  "docstatus": 0,
  "doctype": "Property Setter",
  "doctype_or_field": "DocField",
  "field_name": "scan_barcode",
  "is_system_generated": 1,
  "modified": "2024-12-16 14:24:09.096319",
  "module": null,
  "name": "Sales Invoice-scan_barcode-hidden",
  "property": "hidden",
  "property_type": "Check",
  "row_name": null,
  "value": "0"
 },
 {
  "default_value": null,
  "doc_type": "Material Request",
  "docstatus": 0,
  "doctype": "Property Setter",
  "doctype_or_field": "DocField",
  "field_name": "scan_barcode",
  "is_system_generated": 1,
  "modified": "2024-12-16 14:24:09.109815",
  "module": null,
  "name": "Material Request-scan_barcode-hidden",
  "property": "hidden",
  "property_type": "Check",
  "row_name": null,
  "value": "0"
 },
 {
  "default_value": null,
  "doc_type": "Stock Entry",
  "docstatus": 0,
  "doctype": "Property Setter",
  "doctype_or_field": "DocField",
  "field_name": "scan_barcode",
  "is_system_generated": 1,
  "modified": "2024-12-16 14:24:09.123506",
  "module": null,
  "name": "Stock Entry-scan_barcode-hidden",
  "property": "hidden",
  "property_type": "Check",
  "row_name": null,
  "value": "0"
 },
 {
  "default_value": null,
  "doc_type": "Sales Invoice Item",
  "docstatus": 0,
  "doctype": "Property Setter",
  "doctype_or_field": "DocField",
  "field_name": "target_warehouse",
  "is_system_generated": 0,
  "modified": "2024-12-16 14:24:09.161917",
  "module": null,
  "name": "Sales Invoice Item-target_warehouse-hidden",
  "property": "hidden",
  "property_type": "Check",
  "row_name": null,
  "value": "1"
 },
 {
  "default_value": null,
  "doc_type": "Delivery Note Item",
  "docstatus": 0,
  "doctype": "Property Setter",
  "doctype_or_field": "DocField",
  "field_name": "target_warehouse",
  "is_system_generated": 0,
  "modified": "2024-12-16 14:24:09.183849",
  "module": null,
  "name": "Delivery Note Item-target_warehouse-hidden",
  "property": "hidden",
  "property_type": "Check",
  "row_name": null,
  "value": "1"
 },
 {
  "default_value": null,
  "doc_type": "Purchase Invoice Item",
  "docstatus": 0,
  "doctype": "Property Setter",
  "doctype_or_field": "DocField",
  "field_name": "from_warehouse",
  "is_system_generated": 0,
  "modified": "2024-12-16 14:24:09.199078",
  "module": null,
  "name": "Purchase Invoice Item-from_warehouse-hidden",
  "property": "hidden",
  "property_type": "Check",
  "row_name": null,
  "value": "1"
 },
 {
  "default_value": null,
  "doc_type": "Purchase Receipt Item",
  "docstatus": 0,
  "doctype": "Property Setter",
  "doctype_or_field": "DocField",
  "field_name": "from_warehouse",
  "is_system_generated": 0,
  "modified": "2024-12-16 14:24:09.215074",
  "module": null,
  "name": "Purchase Receipt Item-from_warehouse-hidden",
  "property": "hidden",
  "property_type": "Check",
  "row_name": null,
  "value": "1"
 },
 {
  "default_value": null,
  "doc_type": "Sales Invoice",
  "docstatus": 0,
  "doctype": "Property Setter",
  "doctype_or_field": "DocField",
  "field_name": "customer_section",
  "is_system_generated": 0,
  "modified": "2024-12-16 14:31:45.671582",
  "module": null,
  "name": "Sales Invoice-customer_section-label",
  "property": "label",
  "property_type": "Data",
  "row_name": null,
  "value": "Customer Details"
 }
]